gede/__init__.py
gede/chatcore.py
gede/config.py
gede/encrypt.py
gede/gede.py
gede/profiles.py
gede/top.py
gede/commands/__init__.py
gede/commands/base.py
gede/commands/chat_commands.py
gede/commands/common.py
gede/commands/file_commands.py
gede/commands/instruction_commands.py
gede/commands/model_commands.py
gede/commands/other_commands.py
gede/commands/tool_commands.py
gede/llm/__init__.py
gede/llm/ai302_provider.py
gede/llm/anthropic_provider.py
gede/llm/common_model_settings.py
gede/llm/deepseek_provider.py
gede/llm/generate_title.py
gede/llm/kimi_provider.py
gede/llm/llm_provider.py
gede/llm/model_info.py
gede/llm/openai_provider.py
gede/llm/openrouter_provider.py
gede/llm/providers.py
gede/llm/qwen_provider.py
gede/llm/voice_engine_provider.py
gede/llm/wenxin_provider.py
gede/llm/mcp/mcp_config.py
gede/llm/mcp/mcp_manager.py
gede/llm/tools/__init__.py
gede/llm/tools/read_url_tool.py
gede/llm/tools/time_tool.py
gede/llm/tools/tools.py
gede/llm/tools/web_search.py
gede-0.3.23.dist-info/METADATA
gede-0.3.23.dist-info/WHEEL
gede-0.3.23.dist-info/entry_points.txt
gede-0.3.23.dist-info/licenses/LICENSE
gede-0.3.23.dist-info/RECORD
