Metadata-Version: 2.4
Name: gede
Version: 0.3.23
Summary: A powerful CLI for interacting with multiple LLM providers. Support 10+ providers with smart chat management, encryption, MCP servers, and rich tools ecosystem.
Project-URL: Homepage, https://github.com/adow/gede
Project-URL: Documentation, https://github.com/adow/gede#readme
Project-URL: Repository, https://github.com/adow/gede.git
Project-URL: Bug Tracker, https://github.com/adow/gede/issues
Project-URL: Changelog, https://github.com/adow/gede/blob/main/CHANGELOG.md
Author-email: adow <reynoldqin@gmail.com>
Maintainer-email: adow <reynoldqin@gmail.com>
License: MIT
License-File: LICENSE
Keywords: AI,Anthropic,CLI,ChatGPT,DeepSeek,LLM,OpenAI
Classifier: Development Status :: 4 - Beta
Classifier: Environment :: Console
Classifier: Intended Audience :: Developers
Classifier: Intended Audience :: End Users/Desktop
Classifier: License :: OSI Approved :: MIT License
Classifier: Natural Language :: Chinese (Simplified)
Classifier: Natural Language :: English
Classifier: Operating System :: MacOS
Classifier: Operating System :: Microsoft :: Windows
Classifier: Operating System :: POSIX :: Linux
Classifier: Programming Language :: Python :: 3
Classifier: Programming Language :: Python :: 3.10
Classifier: Programming Language :: Python :: 3.11
Classifier: Programming Language :: Python :: 3.12
Classifier: Programming Language :: Python :: 3.13
Classifier: Topic :: Internet
Classifier: Topic :: Software Development :: Libraries :: Python Modules
Classifier: Topic :: Utilities
Classifier: Typing :: Typed
Requires-Python: >=3.10
Requires-Dist: anyio>=4.9.0
Requires-Dist: cryptography>=44.0.2
Requires-Dist: httpx>=0.28.1
Requires-Dist: inquirer>=3.4.1
Requires-Dist: mcp>=1.12.4
Requires-Dist: openai-agents>=0.2.11
Requires-Dist: prompt-toolkit>=3.0.52
Requires-Dist: pydantic>=2.10.6
Requires-Dist: pyfiglet>=1.0.4
Requires-Dist: python-dotenv==1.0.1
Requires-Dist: rich>=13.9.4
Provides-Extra: arize-trace
Requires-Dist: arize-phoenix-otel>=0.13.1; extra == 'arize-trace'
Requires-Dist: openinference-instrumentation-openai-agents>=1.3.0; extra == 'arize-trace'
